kakuyomu/__init__.py
kakuyomu/logger.py
kakuyomu/cli/__init__.py
kakuyomu/cli/main.py
kakuyomu/cli/commands/__init__.py
kakuyomu/cli/commands/episode.py
kakuyomu/cli/commands/kakuyomu.py
kakuyomu/cli/commands/work.py
kakuyomu/client/__init__.py
kakuyomu/client/client.py
kakuyomu/client/decorators.py
kakuyomu/client/request_models.py
kakuyomu/client/web.py
kakuyomu/scrapers/__init__.py
kakuyomu/scrapers/base.py
kakuyomu/scrapers/episode_page.py
kakuyomu/scrapers/my_page.py
kakuyomu/scrapers/publish_page.py
kakuyomu/scrapers/work_page.py
kakuyomu/settings/__init__.py
kakuyomu/settings/const.py
kakuyomu/settings/work.py
kakuyomu/types/__init__.py
kakuyomu/types/errors.py
kakuyomu/types/path.py
kakuyomu/types/work/__init__.py
kakuyomu/types/work/episode.py
kakuyomu/types/work/episode_query.py
kakuyomu/types/work/work.py
kakuyomu_cli-0.12.5.dist-info/METADATA
kakuyomu_cli-0.12.5.dist-info/WHEEL
kakuyomu_cli-0.12.5.dist-info/entry_points.txt
kakuyomu_cli-0.12.5.dist-info/licenses/LICENSE
kakuyomu_cli-0.12.5.dist-info/RECORD
