Metadata-Version: 2.3
Name: kakuyomu-cli
Version: 0.12.5
Summary: Kakuyomu CLI
Author-email: kokardy <mgc1028@gmail.com>
License: MIT
License-File: LICENSE
Keywords: cli,kakuyomu
Requires-Python: >=3.12
Requires-Dist: beautifulsoup4>=4.12.2
Requires-Dist: coloredlogs>=15.0.1
Requires-Dist: pydantic>=2.5.3
Requires-Dist: requests>=2.31.0
Requires-Dist: toml>=0.10.2
Requires-Dist: types-requests>=2.31.0.20240106
